ColorCraft/Color.py
ColorCraft/Errors.py
ColorCraft/Print.py
ColorCraft/Printv1.py
ColorCraft/Printv2.py
ColorCraft/__init__.py
ColorCraft/__test__.py
ColorCraft-0.3.0.dist-info/LICENCE.txt
ColorCraft-0.3.0.dist-info/METADATA
ColorCraft-0.3.0.dist-info/WHEEL
ColorCraft-0.3.0.dist-info/top_level.txt
ColorCraft-0.3.0.dist-info/RECORD
